[
  {
    "review_id": "173264486",
    "review": "es como ser niño de nuevo , no se aser los puzles tengo 21 años , ayuden me",
    "voted_up": true
  },
  {
    "review_id": "175054895",
    "review": "El videojuego lo compré hoy y no me arranca a la hora de iniciar",
    "voted_up": false
  },
  {
    "review_id": "130544118",
    "review": "O lo jugas teniendo 7 años o lo jugas teniendo mas de 20 no hay punto medio",
    "voted_up": true
  },
  {
    "review_id": "133332573",
    "review": "crashea todo el tiempo",
    "voted_up": false
  },
  {
    "review_id": "192462697",
    "review": "no es el mejor lego batman pero muy bueno para su epoca",
    "voted_up": true
  },
  {
    "review_id": "141341633",
    "review": "Sin duda una obra magna videojugabilistica de la primera decada del siglo XXI.",
    "voted_up": true
  },
  {
    "review_id": "172451052",
    "review": "muchos bugs",
    "voted_up": false
  },
  {
    "review_id": "160007199",
    "review": "Un clasico",
    "voted_up": true
  },
  {
    "review_id": "126394165",
    "review": "Se crahsea mucho y no podes avanzar nunca",
    "voted_up": false
  },
  {
    "review_id": "171703055",
    "review": "Excelente juego entretenido",
    "voted_up": true
  },
  {
    "review_id": "61956501",
    "review": "malardo, mejor en ps2",
    "voted_up": false
  },
  {
    "review_id": "120256819",
    "review": "ta bueno 👍",
    "voted_up": true
  },
  {
    "review_id": "114659630",
    "review": "linda nostalgia",
    "voted_up": true
  },
  {
    "review_id": "88922720",
    "review": "Los juegos de LEGO son definitiviamente de las mejores experiencias coop que el dinero puede comprar.",
    "voted_up": true
  },
  {
    "review_id": "133810700",
    "review": "muy bien juego recomendado :V:V:V:",
    "voted_up": true
  },
  {
    "review_id": "101592134",
    "review": "esta bueno y ayuda a solucionar problemas",
    "voted_up": true
  },
  {
    "review_id": "186846967",
    "review": "me gusta su historia para mi es el mejor juego de lego",
    "voted_up": true
  },
  {
    "review_id": "154174360",
    "review": "me gusta mucho el juego indiana jones la triologia original lego",
    "voted_up": true
  },
  {
    "review_id": "168443039",
    "review": "me quede trabado como un mogolico en un nivel",
    "voted_up": true
  },
  {
    "review_id": "131042984",
    "review": "menudo juego",
    "voted_up": true
  },
  {
    "review_id": "100576948",
    "review": "el juego esta bien, pero tiene muchos bugs, por ejemplo en la ultima mision de acertijo en los villanos se cierra el juego repentinamente",
    "voted_up": false
  },
  {
    "review_id": "91625346",
    "review": "muy  clasico  y disfrutable con mando un poco mas disfrutable pero con un amigo se convierte en risas  total",
    "voted_up": true
  },
  {
    "review_id": "109946599",
    "review": "Si no fuera por los bugs y los crasheos de la primera mision seria un juegazo",
    "voted_up": false
  },
  {
    "review_id": "142237149",
    "review": "Me trae mucha nostalgia. Es de mis legos favoritos",
    "voted_up": true
  },
  {
    "review_id": "113697217",
    "review": "ta bueno",
    "voted_up": true
  },
  {
    "review_id": "77718278",
    "review": "Juego que revive la triologia de Indiana Jones, buenos graficos respecto al anterior y más possibilidades",
    "voted_up": true
  },
  {
    "review_id": "115420912",
    "review": "Ta bueno, compralo urrrraaaaa",
    "voted_up": true
  },
  {
    "review_id": "100318403",
    "review": "si son fans the starwars les va a encantar si no de todos modos les va a gustar",
    "voted_up": true
  },
  {
    "review_id": "132994761",
    "review": "Avisenme cuando arreglen los crasheos",
    "voted_up": false
  },
  {
    "review_id": "92903641",
    "review": "Alguien me puede ayudar a arreglar el bug del auto a control remoto que maneja robin? no me deja jugarlo y no lo quiero rembolsar",
    "voted_up": false
  },
  {
    "review_id": "86360575",
    "review": "INJUGABLE.\nno puedes saltar en las plataformas .... es un fallo que rompe un juego que entretiene mucho pero como dudo que lo actualizen",
    "voted_up": false
  },
  {
    "review_id": "148833126",
    "review": "son god los juegos de legos batman,los recomiendo si quieren pasar un rato.",
    "voted_up": true
  },
  {
    "review_id": "38675573",
    "review": "El juego se cuelga luego de jugarlo unos minutos",
    "voted_up": false
  },
  {
    "review_id": "177314403",
    "review": "Muy bueno, muy nostálgico, muy chimsa",
    "voted_up": true
  },
  {
    "review_id": "113757801",
    "review": "el juego está demasiado mal hecho y creo que hasta se ve mejor en celular",
    "voted_up": false
  },
  {
    "review_id": "136548796",
    "review": "Es perfecto, es simple",
    "voted_up": true
  },
  {
    "review_id": "203465131",
    "review": "Hay varios puntos donde no puedes avanzar y eso hace que no puedas terminar el juego",
    "voted_up": false
  },
  {
    "review_id": "162768606",
    "review": "El juego es pesimo para pc muchos bugs y errores.",
    "voted_up": false
  },
  {
    "review_id": "135520825",
    "review": "muy bueno",
    "voted_up": true
  },
  {
    "review_id": "128244407",
    "review": "Bugs de salto y con algunos trajes .... en fin ni activando el Vsync se pudo :'(",
    "voted_up": false
  },
  {
    "review_id": "44129138",
    "review": "El peor juego que he comprado, es poco intuitivo, aburrido, no sabe uno en ciertas pantallas que es lo que hay que hacer.",
    "voted_up": false
  },
  {
    "review_id": "120251690",
    "review": "tal y como lo recordaba,perfecto",
    "voted_up": true
  },
  {
    "review_id": "31153304",
    "review": "Se queda pillado en mi ordenador haga lo que haga, lo compre donde lo compre.",
    "voted_up": false
  },
  {
    "review_id": "125837940",
    "review": "tremenda obra maestra 20/10 y god",
    "voted_up": true
  },
  {
    "review_id": "95125742",
    "review": "es una porqueria de juego te saca de el",
    "voted_up": false
  },
  {
    "review_id": "128522264",
    "review": "el mejor juego del mundo",
    "voted_up": true
  },
  {
    "review_id": "119966174",
    "review": "juegazo ctm",
    "voted_up": true
  },
  {
    "review_id": "204660854",
    "review": "es bueno para pasar el rato y relajarse e,e",
    "voted_up": true
  },
  {
    "review_id": "141295907",
    "review": "Un clásico",
    "voted_up": true
  },
  {
    "review_id": "114292917",
    "review": "Bro, compralo",
    "voted_up": true
  },
  {
    "review_id": "174899935",
    "review": "se crashea todo el tiempo y esta lleno de bugs no se puede jugar con normalidad",
    "voted_up": false
  },
  {
    "review_id": "173757810",
    "review": "La nostalgia pega duro, ta weno",
    "voted_up": true
  },
  {
    "review_id": "120706279",
    "review": "Nostalgico y sigue siendo un juegazo. 👍💯",
    "voted_up": true
  },
  {
    "review_id": "131440159",
    "review": "Obra de arte en todo su explendor",
    "voted_up": true
  },
  {
    "review_id": "199750762",
    "review": "Básico, pero muy bueno la verdad. Trae muchos recuerdos volver a jugarlo",
    "voted_up": true
  },
  {
    "review_id": "199635026",
    "review": "Juegalo, que sea de lego no significa que sea solo para niños, es uno de los mejores juegos de la historia",
    "voted_up": true
  },
  {
    "review_id": "88981674",
    "review": "buenisimo simplemente.",
    "voted_up": true
  },
  {
    "review_id": "67233980",
    "review": "va fatal no puedo saltar bien y la mitad de los niveles no se pueden pasar",
    "voted_up": false
  },
  {
    "review_id": "148711535",
    "review": "Pesimo. Mal optimizado, mal renderizado. Y encima se cierra solo.",
    "voted_up": false
  },
  {
    "review_id": "116896160",
    "review": "Juegazo de play 2 xd",
    "voted_up": true
  },
  {
    "review_id": "129516516",
    "review": "Tremendo juegazo,encima sale 100 pesos(al momento de escribir esta reseña),un helado sale más plata así que lo recomiendo",
    "voted_up": true
  },
  {
    "review_id": "91598688",
    "review": "los controles son una re paja mal pero se pueden cambiar pero es mas facil jugarlo en play 2",
    "voted_up": false
  },
  {
    "review_id": "92642282",
    "review": "ta bien",
    "voted_up": true
  },
  {
    "review_id": "142708428",
    "review": "buen juego recomendado 7/10",
    "voted_up": true
  },
  {
    "review_id": "109220573",
    "review": "El mejor juego de la historia",
    "voted_up": true
  },
  {
    "review_id": "190395713",
    "review": "no me deja pasar de la primer mision, el cochesito de traba",
    "voted_up": false
  },
  {
    "review_id": "83183415",
    "review": "no se lo compren, no se puede pasar ni siquiera el primer nivel porque esta re bugueado el autito del orto a control remoto",
    "voted_up": false
  },
  {
    "review_id": "111777941",
    "review": "lo jugaba en el plei 2 me trae muchos recuerdos la verdad mui bueno",
    "voted_up": true
  },
  {
    "review_id": "116796134",
    "review": "infancia pura",
    "voted_up": true
  },
  {
    "review_id": "108984921",
    "review": "tremenda obra maestra",
    "voted_up": true
  },
  {
    "review_id": "123299366",
    "review": "una mierda, no arreglan los bugs, te quita la emoción de jugar",
    "voted_up": false
  },
  {
    "review_id": "141187355",
    "review": "Nostalgia from Xbox360",
    "voted_up": true
  },
  {
    "review_id": "208664007",
    "review": "nada mal",
    "voted_up": true
  },
  {
    "review_id": "90283741",
    "review": "Tiene unos bugs que no deja continuar con la historia, este bug esta al pricipio cuando tienes que pasar un carrito por un agujero",
    "voted_up": false
  },
  {
    "review_id": "125539299",
    "review": "Se me buguea siempre en la parte que hay que usar el auto a control remoto, me tiene los huevos llenos",
    "voted_up": false
  },
  {
    "review_id": "90091750",
    "review": "se crashea muy a menudo",
    "voted_up": false
  },
  {
    "review_id": "134929276",
    "review": "Calificacion: 1000/10",
    "voted_up": true
  },
  {
    "review_id": "133261172",
    "review": "se Bugea al saltar",
    "voted_up": false
  },
  {
    "review_id": "202967275",
    "review": "ijos de prra se crashea cada rato los vouy a matar",
    "voted_up": false
  },
  {
    "review_id": "193312658",
    "review": "un gran juego de lego pero no llega a la misma mesa que el anterior juego en resumen esta infravalorado",
    "voted_up": true
  },
  {
    "review_id": "127331701",
    "review": "el juego se buggea cuando uso a robin y trato de manejar el carrito",
    "voted_up": false
  },
  {
    "review_id": "22729561",
    "review": "El peor de todos los juegos LEGO que he jugado, si queréis un batman LEGO, jugad al 2 y al 3 no a este",
    "voted_up": false
  },
  {
    "review_id": "206536062",
    "review": "Juego divertido y corto. Si te gustan los juegos de lego o piratas del caribe, te gustará",
    "voted_up": true
  },
  {
    "review_id": "118766667",
    "review": "al inicio hay un bug con el minicoche de robin que no te deja avanzar.",
    "voted_up": false
  },
  {
    "review_id": "74956202",
    "review": "ta bueno compralo",
    "voted_up": true
  },
  {
    "review_id": "117035889",
    "review": "lleno de bugs lamentable no podes pasar algunas misiones",
    "voted_up": false
  },
  {
    "review_id": "50561041",
    "review": "El Juego bien, pero se queda pillado cada rato, mil de Bug.... que pena",
    "voted_up": false
  },
  {
    "review_id": "177375265",
    "review": "Es Good XD",
    "voted_up": true
  },
  {
    "review_id": "147003377",
    "review": "que mal la gente que no compro este juego antes de que suban exageradamente los precios.",
    "voted_up": true
  },
  {
    "review_id": "142445872",
    "review": "El mejor juego de lego de la historia.",
    "voted_up": true
  },
  {
    "review_id": "182385142",
    "review": "El juego de mi infancia. El mejor juego de Star Wars. No hay discusión al respecto.",
    "voted_up": true
  },
  {
    "review_id": "77593185",
    "review": "Buen juego basado en las peliculas es super recomendable uno de los mejores juegos de Lego no tardes y compralo",
    "voted_up": true
  },
  {
    "review_id": "149574892",
    "review": "esta mierda esta toda bugeada y sale 1400 pesos????????????????",
    "voted_up": true
  },
  {
    "review_id": "118211026",
    "review": "Es el juego con mas bugs de todo Steam, injugable.",
    "voted_up": false
  },
  {
    "review_id": "128879160",
    "review": "Es increible",
    "voted_up": true
  },
  {
    "review_id": "114245186",
    "review": "Buen juego👍",
    "voted_up": true
  },
  {
    "review_id": "168736529",
    "review": "es muy bueno csm",
    "voted_up": true
  },
  {
    "review_id": "164787402",
    "review": "es muy weno",
    "voted_up": true
  },
  {
    "review_id": "181422210",
    "review": "Es un f a kin juegazo obra maestra si este juego tuviera pilin se lo cromaria sin pensarlo 2 veces.",
    "voted_up": true
  },
  {
    "review_id": "202887838",
    "review": "juegazo pero en pc anda re mal, no puedo pasar ni la primer misión que me crashea el juego :(.",
    "voted_up": false
  },
  {
    "review_id": "204877138",
    "review": "Esta buenisimo!",
    "voted_up": true
  },
  {
    "review_id": "94430783",
    "review": "Si van a jugarlo con amigos, no lo recomiendo ya que vienen con problemas de crasheo, una lastima.",
    "voted_up": false
  },
  {
    "review_id": "135872545",
    "review": "es el juego que mas plasma mi infancia/adolecencia, me trae muy lindos recuerdos y sin duda representa muy bien la pelicula, aguante indiana jones wachoooo!!",
    "voted_up": true
  },
  {
    "review_id": "202683032",
    "review": "Si piensas comprarlo, ahorrate tu dinero, esta lleno de bugs que hacen imposible el progreso, una verdadera pena",
    "voted_up": false
  },
  {
    "review_id": "206893372",
    "review": "lleno de bug y crasheo",
    "voted_up": false
  },
  {
    "review_id": "123265322",
    "review": "la verdad es aroma a nostalgia un juegaso que llevo jugando desde niño en la PSP, 100% recomendado",
    "voted_up": true
  },
  {
    "review_id": "135138203",
    "review": "me lo pase en 3 dias xd",
    "voted_up": true
  },
  {
    "review_id": "94587077",
    "review": "Sonidos bugueados que me recuerdan a una estancia en el averno. Es injugable con esos sonidos, ayuda.",
    "voted_up": false
  },
  {
    "review_id": "169465564",
    "review": "se crashea a cada rato y no es que tenga una mala pc",
    "voted_up": false
  },
  {
    "review_id": "184066391",
    "review": "refleja mi infancia este juego",
    "voted_up": true
  },
  {
    "review_id": "34691979",
    "review": "Excelente juego. Muy buenos gráficos como toda la saga Lego. Sigue las cuatro pelis de pirata del Caribe muy fielmente bien al estilo Lego",
    "voted_up": true
  },
  {
    "review_id": "78966483",
    "review": "un gran juego muchas risas no te arrepentiras",
    "voted_up": true
  },
  {
    "review_id": "199576814",
    "review": "Un Clasico que aun es una Perfecion...",
    "voted_up": true
  },
  {
    "review_id": "206565033",
    "review": "ta piola",
    "voted_up": true
  },
  {
    "review_id": "87255466",
    "review": "Se me cierra el juego de forma automatica a los minutos de juego, estoy jugando con un Acer Nitro 5, reinstale y continua el problema.",
    "voted_up": false
  },
  {
    "review_id": "118719653",
    "review": "se me esta cerrando apenas entro en la segunda parte de la pelea de cara de barro",
    "voted_up": false
  },
  {
    "review_id": "138868549",
    "review": "GOTY AS F",
    "voted_up": true
  },
  {
    "review_id": "161909679",
    "review": "muy lineal",
    "voted_up": false
  },
  {
    "review_id": "85789323",
    "review": "esta wueno lo malo que esta en ingle...",
    "voted_up": true
  },
  {
    "review_id": "97146907",
    "review": "ES GOD QUE ESPERAS, CUANDO ESTE EN DESCUENTO A 56 PESITOS TE LO COMPRAS PORQUE TA RE PIOLA",
    "voted_up": true
  },
  {
    "review_id": "109426594",
    "review": "De lo mejor",
    "voted_up": true
  },
  {
    "review_id": "158284956",
    "review": "ta chingon",
    "voted_up": true
  },
  {
    "review_id": "142549902",
    "review": "en ciertos momentos se cierra la app",
    "voted_up": false
  },
  {
    "review_id": "142375765",
    "review": "Hermosa saga recomendada para recordar lo bueno que fue la trilogía de star wars",
    "voted_up": true
  },
  {
    "review_id": "74283021",
    "review": "primer nivel bugeado",
    "voted_up": false
  },
  {
    "review_id": "91319000",
    "review": "el mejor juego de la vida",
    "voted_up": true
  },
  {
    "review_id": "158781489",
    "review": "Esta bien chido el juego. Lor recomiendo ampliamente.",
    "voted_up": true
  },
  {
    "review_id": "95567692",
    "review": "la poronga esta se me crashea cada 10 minutos y cuando mi pc aguanta juegos mucho mas pesados",
    "voted_up": false
  },
  {
    "review_id": "55645115",
    "review": "Tiene bastantes bugs , lo he probado en otras plataformas y es un buen juego pero en pc falla mas que la renfe",
    "voted_up": false
  },
  {
    "review_id": "120750755",
    "review": "El carrito de Robin se queda bugiado no se puede pasar el  1 nivel",
    "voted_up": false
  },
  {
    "review_id": "166970790",
    "review": "Lo jugaba con mi padre de pequeño, ahora que lo compré podré terminarlo junto a él",
    "voted_up": true
  },
  {
    "review_id": "203170841",
    "review": "Juego decente, pero se le nota la edad al hacerse bastante monótono",
    "voted_up": false
  },
  {
    "review_id": "129059762",
    "review": "ES UNA MIERDA NOOOOOOOOOOOOOOOOOOOOOOOOOOOOOOOOOOOOOOOOO, REEEEEEEEEEEEEEEEEEEEEEECOOOOOOOOOOOOOOOOOOOOOOOOOOOOOOOOOOMEEEEEEEEEEEEEEEEEEEEEEEEEEEEEEENDAAAAAAAAAAAAAAAAAAAAAAAAAAAAAAAAAAAAAABLEEEEEEEEEEEEEEEEEEEEEEEEEEE.  CHUMENPE EL PICO MARICONES CONCHETUMARES.",
    "voted_up": false
  },
  {
    "review_id": "49838839",
    "review": "que mala la animacion, ni siquiera esta hecho de 3d. Que lástima .",
    "voted_up": false
  },
  {
    "review_id": "183135927",
    "review": "obra maestra",
    "voted_up": true
  },
  {
    "review_id": "114407767",
    "review": "Esta lleno de bugs que lo vuelven muy pesado.Pero es un clásico de la ps2",
    "voted_up": false
  },
  {
    "review_id": "129852324",
    "review": "buen juego",
    "voted_up": true
  },
  {
    "review_id": "111838576",
    "review": "juegazo . juegenlo putitos",
    "voted_up": true
  },
  {
    "review_id": "143782458",
    "review": "El mejor de la trilogía.",
    "voted_up": true
  },
  {
    "review_id": "177978441",
    "review": "no lo puedo jugar, juego 5 minutos y se crashea una poronga",
    "voted_up": false
  },
  {
    "review_id": "52896068",
    "review": "Muy infantil",
    "voted_up": false
  },
  {
    "review_id": "148883526",
    "review": "Que asco de juego",
    "voted_up": false
  },
  {
    "review_id": "92487725",
    "review": "El juego esta lleno de bugs y se crashea.",
    "voted_up": false
  },
  {
    "review_id": "138392245",
    "review": "tiene demasiados bug en los niveles",
    "voted_up": false
  },
  {
    "review_id": "118289442",
    "review": "excelente juego",
    "voted_up": true
  },
  {
    "review_id": "173161325",
    "review": "no puedo mover el auto del primer nivel y encima no puedo pasarme ningun nivel porque el autito de control no se mueve",
    "voted_up": false
  },
  {
    "review_id": "167782571",
    "review": "esta mal porteado chale",
    "voted_up": false
  },
  {
    "review_id": "129730835",
    "review": "Que buen juego hermano, totalmente recomendado sobre todo si lo jugaste en PS2 y nunca te lo pasate",
    "voted_up": true
  },
  {
    "review_id": "129318157",
    "review": "Aburre :C",
    "voted_up": false
  },
  {
    "review_id": "181679583",
    "review": "lo recordaba mejor :c",
    "voted_up": false
  },
  {
    "review_id": "133643924",
    "review": "buen juego",
    "voted_up": true
  },
  {
    "review_id": "191120020",
    "review": "Sencillo, desestresante. Ideal para niños y personas que solo quieren relajarse",
    "voted_up": true
  },
  {
    "review_id": "203659285",
    "review": "Se cierra solo el juego.",
    "voted_up": false
  },
  {
    "review_id": "113023416",
    "review": "bueno de a dos personas, si no, no lo vale",
    "voted_up": true
  },
  {
    "review_id": "126011333",
    "review": "el segundo mejor juego de lego starwars, la mejor banda sonora y los personajes mas lindos uwu",
    "voted_up": true
  },
  {
    "review_id": "143489563",
    "review": "crasheos del caribe",
    "voted_up": false
  },
  {
    "review_id": "120582436",
    "review": "buen juego de lego y batman, recomendable para computadoras con pocos requisitos, da diversion, muy entretenido, recomendable",
    "voted_up": true
  },
  {
    "review_id": "35589044",
    "review": "un excelente lego lo unico malo los crasheos inesperados, hace que no se guarde la partida",
    "voted_up": false
  },
  {
    "review_id": "44007580",
    "review": "El peor juego de Lego, y por lejos",
    "voted_up": false
  },
  {
    "review_id": "164241180",
    "review": "JUEGAZO, de verdad que es tremendo juego, me trae mucha nostalgia de cuando lo jugaba en PS2 con mi hermano pequeño.",
    "voted_up": true
  },
  {
    "review_id": "203926400",
    "review": "Buen Juego",
    "voted_up": true
  },
  {
    "review_id": "201702990",
    "review": "es lindo volver a jugarlo desde que jugaba la PS2",
    "voted_up": true
  },
  {
    "review_id": "134658026",
    "review": "Este juego me trae muchos recuerdos de cuando era pequeño y no tenia que estudiar. Like si te gustan los Legos",
    "voted_up": true
  },
  {
    "review_id": "123503470",
    "review": "Muy bueno para los fans",
    "voted_up": true
  },
  {
    "review_id": "194856493",
    "review": "me gusto, lo jugaba desde q tenia 8 años en el playstation 3",
    "voted_up": true
  },
  {
    "review_id": "206160637",
    "review": "uno de los juegos de mi infancia, pero la version de steam es injugable, da tirones a cada rato, lamentable",
    "voted_up": false
  },
  {
    "review_id": "160819086",
    "review": "JUEGAZO DE LA INFANCIA",
    "voted_up": true
  },
  {
    "review_id": "182675175",
    "review": "Muy divertido\r\n}",
    "voted_up": true
  },
  {
    "review_id": "155124742",
    "review": "Está difícil .",
    "voted_up": false
  },
  {
    "review_id": "156557944",
    "review": "juegaso clasico",
    "voted_up": true
  },
  {
    "review_id": "117662018",
    "review": "porque lees esto? COMPRALO",
    "voted_up": true
  },
  {
    "review_id": "50867038",
    "review": "Juego entretenido sin muchas aspiraciones... pero es que tiene muchos fallos y bugs que me están haciendo crashear el juego y no me dejan avanzar.",
    "voted_up": false
  },
  {
    "review_id": "158021429",
    "review": "el juego es tan fiel a los comics q te vuelves loco como el joker jugandolo de lo bueno q es",
    "voted_up": true
  },
  {
    "review_id": "77790467",
    "review": "Buen juego, horrible versión.\n\nPD: No importa que uses la Sincronización Vertical (VSync). \n      El juego se te cerrara igual.",
    "voted_up": false
  },
  {
    "review_id": "201283132",
    "review": "Es un juego historico y deberían jugarlo, pero es que la versión de PC está llena de bugs lo siento.",
    "voted_up": false
  },
  {
    "review_id": "107275959",
    "review": "Buen juego para pasar el rato",
    "voted_up": true
  },
  {
    "review_id": "160964390",
    "review": "el mejor juego de lego, lo compré como 4 veces en la play 2 pork el disco ctm se pasaba rayando",
    "voted_up": true
  },
  {
    "review_id": "162147575",
    "review": "es un juegazo y el mejor de lego",
    "voted_up": true
  },
  {
    "review_id": "114033172",
    "review": "El juego esta lleno de bugs y se crashea todo el tiempo , injugable el auto no se puede mover",
    "voted_up": false
  },
  {
    "review_id": "202852022",
    "review": "batman lego hombre feliz",
    "voted_up": true
  },
  {
    "review_id": "94687078",
    "review": "se crashea y no puedo terminar los niveles",
    "voted_up": false
  },
  {
    "review_id": "110034230",
    "review": "Mejor juego de Lego, historia pura.",
    "voted_up": true
  },
  {
    "review_id": "109420098",
    "review": "no me deja jugar de a un solo jugador. (me pone dos dispositivos para jugar automáticamente)\ncomo hago para jugarlo yo solo?",
    "voted_up": false
  },
  {
    "review_id": "133139537",
    "review": "es bueno",
    "voted_up": true
  },
  {
    "review_id": "204351631",
    "review": "la compatibilidad con mando es muy mala, y hay algunas partes en las que te ves obligado a jugar con teclado",
    "voted_up": false
  },
  {
    "review_id": "129817201",
    "review": "ME ENAMORE DE ESTE JUEGOOOOO",
    "voted_up": true
  },
  {
    "review_id": "168302925",
    "review": "muy buena saga de videojuegos",
    "voted_up": true
  },
  {
    "review_id": "202324224",
    "review": "Es un juegazo de la infancia que todavia entretiene a pesar de los años que han pasado",
    "voted_up": true
  },
  {
    "review_id": "203291037",
    "review": "No ha envejecido mal el juego y sigue siendo divertido pero los bugs que tiene son insufribles",
    "voted_up": false
  },
  {
    "review_id": "200240138",
    "review": "NO SE PUEDE JUGAR.\nESTA LLENOS DE BUGS Y NO PODES PROGRESAR. \nARREGLEN ESTE JUEGO PORFAVOR.",
    "voted_up": false
  },
  {
    "review_id": "159537084",
    "review": "es un juego de mi infancia que me encanta pero el juego me crashea y se bugea demasiado",
    "voted_up": false
  },
  {
    "review_id": "114037531",
    "review": "la cantidad de bugs que tiene es una locura, lo tuve que dejar de jugar por los bugs.",
    "voted_up": false
  },
  {
    "review_id": "152623157",
    "review": "no puedo jugarlo, me da pantalla negra y no eh podido probarlo",
    "voted_up": false
  },
  {
    "review_id": "34609476",
    "review": "Cualquier parecido con las peliculas originales es pura coincidencia",
    "voted_up": false
  },
  {
    "review_id": "141811556",
    "review": "infancia (obra maestra)",
    "voted_up": true
  },
  {
    "review_id": "197826707",
    "review": "Ha envejecido bastante mal, la cámara si juegas con varios personajes no funciona muy bien",
    "voted_up": false
  },
  {
    "review_id": "170056904",
    "review": "Lllevo jugandolo algunas horas y el juego se cierra solo, esta bueno pero es el defecto que tiene, y mala pc no tengo",
    "voted_up": false
  },
  {
    "review_id": "104084396",
    "review": "que juegazo 11/10",
    "voted_up": true
  },
  {
    "review_id": "185876024",
    "review": "Simplemente el mejor juego de lego star wars de la P\"#& HISTORIA !\r\n\r\n11/10",
    "voted_up": true
  },
  {
    "review_id": "95416953",
    "review": "Un juego clasico es un 10 de 10 mucha nostalgia para los fanes de star wars.",
    "voted_up": true
  },
  {
    "review_id": "116010291",
    "review": "tremendo juego 10/10, el robin me recuerda a mi solo que yo soy mas espantaviejas",
    "voted_up": true
  },
  {
    "review_id": "179613277",
    "review": "Este juego es cine 🚬",
    "voted_up": true
  },
  {
    "review_id": "204632355",
    "review": "actualmente es injugable no puedo pasarme el nivel 2-3 porque no me deja saltar en x puntos de sitios como en la válvula roja",
    "voted_up": false
  },
    {
    "review_id": "190430215",
    "review": "bueno, no estoy muy familiarizado con la jugabilidad, pero es de jurassic y me ecanta.",
    "voted_up": true
  },
  {
    "review_id": "91562890",
    "review": "⣿⣿⣿⣿⣿⣿⣿⣿⣿⣿⣿⣿⣿⣿⣿⣿⣿⣿⣿⣿⣿⣿⣿⣿\n⣿ta bueno ⣿⣿⣿⣿⣿⣿⣿⣿⣿⣿⣿⣿⣿⣿⣿⣿⣿\n⣿⣿⣿⣿⣿⣿⣿⣿⡿⢋⣩⣭⣶⣶⣮⣭⡙⠿⣿⣿⣿⣿⣿⣿\n⣿⣿⣿⣿⣿⣿⠿⣋⣴⣿⣿⣿⣿⣿⣿⣿⣿⣿⣦⡙⢿⣿⣿⣿\n⣿⣿⣿⣿⣿⡃⠄⠹⡿⣿⣿⣿⣿⠟⠛⣿⣿⣿⣿⣷⡌⢿⣿⣿\n⣿⣿⣿⣿⣿⠐⣠⡶⣶⣲⡎⢻⣿⣤⣴⣾⣿⣿⣿⣿⣿⠸⣿⣿\n⣿⠟⣋⡥⡶⣞⡯⣟⣾⣺⢽⡧⣥⣭⣉⢻⣿⣿⣿⣿⣿⣆⢻⣿\n⡃⣾⢯⢿⢽⣫⡯⣷⣳⢯⡯⠯⠷⠻⠞⣼⣿⣿⣿⣿⣿⣿⡌⣿\n⣦⣍⡙⠫⠛⠕⣋⡓⠭⣡⢶⠗⣡⣶⡝⣿⣿⣿⣿⣿⣿⣿⣧⢹\n⣿⣿⣿⣿⣿⣿⣘⣛⣋⣡⣵⣾⣿⣿⣿⢸⣿⣿⣿⣿⣿⣿⣿⢸\n⣿⣿⣿⣿⣿⣿⣿⣿⣿⣿⣿⣿⣿⣿⣿⢸⣿⣿⣿⣿⣿⣿⣿⢸\n⣿⣿⣿⣿⣿compralo ⣿⣿⣿⣿⢸⣿⣿⣿⣿⣿⣿⣿⢸",
    "voted_up": true
  },
  {
    "review_id": "56973744",
    "review": "eta buena :D",
    "voted_up": true
  },
  {
    "review_id": "186453267",
    "review": "Nada q decir,juegazo,jueguenlo\nmecanica sencilla como cualquier otro lego,pero mejor\njueguen esta joyita\nRecomendado al 100%\n(Nada q decir,juegazo completado al 100%)",
    "voted_up": true
  },
  {
    "review_id": "127693055",
    "review": "muy bueno fue mi infancia",
    "voted_up": true
  },
  {
    "review_id": "52543432",
    "review": "una mierda",
    "voted_up": false
  },
  {
    "review_id": "208446171",
    "review": "muy buen juego 100 de 10 muy nostalgico",
    "voted_up": true
  },
  {
    "review_id": "153619336",
    "review": "devuelvanme el juego",
    "voted_up": false
  },
  {
    "review_id": "176842094",
    "review": "ES DIVERTIDO Y UN POCO DIFICIL PERO LA VERDAD ESTE JUEGO ME MARCO UNA INFANCIA INCREIBLE",
    "voted_up": true
  },
  {
    "review_id": "114959684",
    "review": "NO PUEDO PONER EL SELECTOR DE PERSONAJEEE",
    "voted_up": false
  },
  {
    "review_id": "165380263",
    "review": "Esta bugeada la primera mision cuando sale el tren",
    "voted_up": false
  },
  {
    "review_id": "15682417",
    "review": "el juego es una pasada le doy tres millones de estrellas xD",
    "voted_up": true
  },
  {
    "review_id": "170721268",
    "review": "muy bueno.",
    "voted_up": true
  },
  {
    "review_id": "180609802",
    "review": "Francamente, el mejor juego de marvel",
    "voted_up": true
  },
  {
    "review_id": "95294611",
    "review": "bastante nefasto la verdad te aburre a los 10 minutos",
    "voted_up": false
  },
  {
    "review_id": "117601142",
    "review": "esta bueno pero saquen el audio en español",
    "voted_up": true
  },
  {
    "review_id": "43490736",
    "review": "Le baje la calidad al sombreado y ahora no me abre el juego",
    "voted_up": false
  },
  {
    "review_id": "70692530",
    "review": "se me borro la partida",
    "voted_up": false
  },
  {
    "review_id": "118581585",
    "review": "El juego no funciona  se corrompen las partidas y es imposible completarlo.",
    "voted_up": false
  },
  {
    "review_id": "52964649",
    "review": "Un gran juego si eres un fan de los juegos lego o de los dinosaurios",
    "voted_up": true
  },
  {
    "review_id": "127070294",
    "review": "Es super poder jugar las historias en modo libre",
    "voted_up": true
  },
  {
    "review_id": "149046910",
    "review": "Ta bueno",
    "voted_up": true
  },
  {
    "review_id": "109227777",
    "review": "no lo recomiendo por que el ultimo nivel no lo podia pasar tipo se bugeaba y no podia completarlo",
    "voted_up": false
  },
  {
    "review_id": "196494503",
    "review": "me mola mas el star wars lego pero reconozco con mucha seguridad y respeto que este es el mejor juego de lego de todos.",
    "voted_up": true
  },
  {
    "review_id": "123567059",
    "review": "muy buen juego",
    "voted_up": true
  },
  {
    "review_id": "146776797",
    "review": "Ojala metan una actualizacion del Lego: Jurassic World ambientadas en Fallen Kingdom Y Dominion",
    "voted_up": true
  },
  {
    "review_id": "13234186",
    "review": "Bugea demasiado, hay puntos que directamente no los han probado. Es muy distinto al resto de la saga LEGO, tanto en humor como en gameplay.",
    "voted_up": false
  },
  {
    "review_id": "122160857",
    "review": "nefasto todo bugeado juego de mierda",
    "voted_up": false
  },
  {
    "review_id": "198465467",
    "review": "Demasiados bugs, si no es por un foro que encontré nunca podría haber solucionado el problema del crasheo en Bree",
    "voted_up": false
  },
  {
    "review_id": "37912884",
    "review": "Lindo Lego, lindo juego, pero muchos bugs que te hacen doler la cabeza",
    "voted_up": false
  },
  {
    "review_id": "8419570",
    "review": "Excelente juego no duden en comprarlo es genial !!",
    "voted_up": true
  },
  {
    "review_id": "115127753",
    "review": "simplemente hermoso, es el tipico juego que jugabas de niño solo que este no te decepciona de grande",
    "voted_up": true
  },
  {
    "review_id": "36502090",
    "review": "pesimo, el juego no me deja guardar partidas, siempre me envia al inicio de todas las misiones",
    "voted_up": false
  },
  {
    "review_id": "49280127",
    "review": "Es un lego. ¿Qué mas quieres?\n\nIdeal el coop.",
    "voted_up": true
  },
  {
    "review_id": "168289201",
    "review": "es un buen juego facil de pasar pero cumple con su proposito",
    "voted_up": true
  },
  {
    "review_id": "120369426",
    "review": "hermoso y epico",
    "voted_up": true
  },
  {
    "review_id": "142517026",
    "review": "No deja entrar al juego",
    "voted_up": false
  },
  {
    "review_id": "188285349",
    "review": "lo puntuaria bien si por lo menos me dejara entrar al juego",
    "voted_up": false
  },
  {
    "review_id": "142091664",
    "review": "Es lego xdxdxddx god",
    "voted_up": true
  },
  {
    "review_id": "29863085",
    "review": "Lo recomiendo tienes un control. Jugarlo con teclado es una experiencia que no quieres pasar.",
    "voted_up": true
  },
  {
    "review_id": "70997059",
    "review": "Devuelvanme la gita la puta que lo pario lo peor es  que hasta el lego batman 1 es mejor",
    "voted_up": false
  },
  {
    "review_id": "128443055",
    "review": "PORONGA DE JUEGO SE TE DAÑAN LAS PARTIDAS",
    "voted_up": false
  },
  {
    "review_id": "133230927",
    "review": "Probablemente el mejor lego",
    "voted_up": true
  },
  {
    "review_id": "48129806",
    "review": "NO\nBasura",
    "voted_up": false
  },
  {
    "review_id": "38981538",
    "review": "Para ser juego de Lego, está muy bien logrado con un humor simple pero divertido para las 4 películas.",
    "voted_up": true
  },
  {
    "review_id": "47901442",
    "review": "baya que joyita ya veo por que lo regalaron... esto es un juego para llorar y no para divertirse...",
    "voted_up": false
  },
  {
    "review_id": "195036279",
    "review": "buen lego",
    "voted_up": true
  },
  {
    "review_id": "36049416",
    "review": "es una cosa solo para niños que no saben jugar",
    "voted_up": false
  },
  {
    "review_id": "9877761",
    "review": "El sistema de juego es excelente , la verdad esta muy centrado en la trilogia de la pelicula me gusto mucho",
    "voted_up": true
  },
  {
    "review_id": "198571851",
    "review": "goood infancia y todo",
    "voted_up": true
  },
  {
    "review_id": "142248981",
    "review": "Buenardo con el Remote Play Together",
    "voted_up": true
  },
  {
    "review_id": "156502554",
    "review": "una verga",
    "voted_up": false
  },
  {
    "review_id": "20346656",
    "review": "Los peores controles que he probado en mi vida",
    "voted_up": false
  },
  {
    "review_id": "48496850",
    "review": "Ahhhh que recuerdos cuando solia jugar el lego star wars en la play 2.....pero este almenos tiene mucho mas mundo abierto =^=",
    "voted_up": true
  },
  {
    "review_id": "207826079",
    "review": "muy bueno, se merece el goty. Muy buen juego de exploracion 10 de 10 :)",
    "voted_up": true
  },
  {
    "review_id": "116470401",
    "review": "estafadoresssssssss no se oye nada....soluciones¿?\nel dinero si que lo cobran..por un juego que no se oye...vaya estafa",
    "voted_up": false
  },
  {
    "review_id": "94747209",
    "review": "lleno de bugs, no puedo pasar la primera parte xq se buguea el camion y no deja ir marcha atras",
    "voted_up": false
  },
  {
    "review_id": "142497369",
    "review": "MIIIIIIIIIIEEEEEEEEEEEEEEEEEEEEEEEEEEEEEEEEEERDAAAAAAAAAAAAAAAAAAAAAAAAAAAAAAAAAAA TOOOOOOOOOOOOOOOOOOOOOOOOOOOOOOOOOOTAAAAAAAAAAAAAAAAAAAAAAAAL",
    "voted_up": false
  },
  {
    "review_id": "188260016",
    "review": "Un juego bastante entretenido y creativo para pasar el tiempo con la familia, me gusta mucho",
    "voted_up": true
  },
  {
    "review_id": "168985951",
    "review": "Será el GOTY del siglo? 100/10",
    "voted_up": true
  },
  {
    "review_id": "176388143",
    "review": "Buen juego, dislike",
    "voted_up": true
  },
  {
    "review_id": "47792173",
    "review": "Se cierra el juego después de la persecución a Frodo en el bosque (en los inicios).",
    "voted_up": false
  },
  {
    "review_id": "75376501",
    "review": "Ta bien.",
    "voted_up": true
  },
  {
    "review_id": "19230407",
    "review": "el guego se traba demaciado y no se puede ni jugar 5 minutos bien",
    "voted_up": false
  },
  {
    "review_id": "171650895",
    "review": "buen juego",
    "voted_up": true
  },
  {
    "review_id": "155132634",
    "review": "Es una maravilla de juego para los fanáticos del señor de los anillos, con muchos rompecabezas divertidos y con controles muy fáciles",
    "voted_up": true
  },
  {
    "review_id": "66679108",
    "review": "Otra maravilla de LEGO!",
    "voted_up": true
  },
  {
    "review_id": "130392275",
    "review": "Muy god",
    "voted_up": true
  },
  {
    "review_id": "29674059",
    "review": "No es nada intuitivo, mal diseño de niveles",
    "voted_up": false
  },
  {
    "review_id": "78429804",
    "review": "ta weno",
    "voted_up": true
  },
  {
    "review_id": "186552817",
    "review": "Una Basura el juego encima al conectar los dos joystick uno falla y el otro no, re aburrido no lo recomiendo",
    "voted_up": false
  },
  {
    "review_id": "136857622",
    "review": "Si te gustan las películas de \"Jurassic Park\" y \"Jurassic World\" y además, te gusta LEGO, es tu juego ideal!\nLo recomiendo 100%",
    "voted_up": true
  },
  {
    "review_id": "74305478",
    "review": "esta bueno y todavia no me lo completé al 100%.",
    "voted_up": true
  },
  {
    "review_id": "109057288",
    "review": "esta entretenido, sobre todo con alguien",
    "voted_up": true
  },
  {
    "review_id": "118007696",
    "review": "Un juego bastante sencillo y fácil de aprender... Lo considero una muy buena opción para pasar el rato ;)",
    "voted_up": true
  },
  {
    "review_id": "184952766",
    "review": "hermoso juego",
    "voted_up": true
  },
  {
    "review_id": "142394431",
    "review": "que nostalgia (me da un embole este juego)",
    "voted_up": true
  },
  {
    "review_id": "47692233",
    "review": "vaya puta mierda",
    "voted_up": false
  },
  {
    "review_id": "160404652",
    "review": "LEGO X MARAVEL",
    "voted_up": true
  },
  {
    "review_id": "138642216",
    "review": "Revender mis legos me está dando bastante pasta!",
    "voted_up": false
  },
  {
    "review_id": "120343974",
    "review": "es un poco aburrido porque es como que todo esta ahi cerrado todo es muy cerrado la historia es muy cerrada",
    "voted_up": false
  },
  {
    "review_id": "136589985",
    "review": "TA BUENO",
    "voted_up": true
  },
  {
    "review_id": "138369526",
    "review": "Buen juego para distraerse un buen rato",
    "voted_up": true
  },
  {
    "review_id": "21614879",
    "review": "Excelente y muy divertido el juego al poder experimentar todas las peliculas de Jurassic Park",
    "voted_up": true
  },
  {
    "review_id": "153547484",
    "review": "q triste",
    "voted_up": false
  },
  {
    "review_id": "48961364",
    "review": "Safa, pero no me convence!!",
    "voted_up": false
  },
  {
    "review_id": "117248599",
    "review": "piola xd un capo",
    "voted_up": true
  },
  {
    "review_id": "54155879",
    "review": "bueno para niños rata",
    "voted_up": false
  },
  {
    "review_id": "102950503",
    "review": "El Señor de los Anillos. Ahora con un 25% más de humor.",
    "voted_up": true
  },
  {
    "review_id": "69379400",
    "review": "No esta en español no pierdan el tiempo.",
    "voted_up": false
  },
  {
    "review_id": "64569627",
    "review": "es buenardooooo",
    "voted_up": true
  },
  {
    "review_id": "70072895",
    "review": "es mui bueno y porta buna imajinasion",
    "voted_up": true
  },
  {
    "review_id": "39768995",
    "review": "Muy buen juego asegura horas de etretencion intentado desbloquear personajes y buscar los objetos ocultos",
    "voted_up": true
  },
  {
    "review_id": "190585630",
    "review": "este juego es una joya del 2014, y su soundtrack uff hermoso",
    "voted_up": true
  },
  {
    "review_id": "129134434",
    "review": "ME iso acordar mi infancia",
    "voted_up": true
  },
  {
    "review_id": "140080251",
    "review": "Juego de mierda malo y bugeado.",
    "voted_up": false
  },
  {
    "review_id": "165498114",
    "review": "Juego entretenido, fácil de entender y con buena historia",
    "voted_up": true
  },
  {
    "review_id": "68504990",
    "review": "No consigo jugar con mi mando de ps4, alguien me ayuda?",
    "voted_up": true
  },
  {
    "review_id": "97449585",
    "review": "Dios mio la nostalgia señor",
    "voted_up": true
  },
  {
    "review_id": "127556024",
    "review": "buen juego como asi todos los de la franquicia lego las bromas son geniales",
    "voted_up": true
  },
  {
    "review_id": "190517542",
    "review": "fckin joya cinematográfica",
    "voted_up": true
  },
  {
    "review_id": "48767290",
    "review": "LA VERDAD QUE MUY BUENA",
    "voted_up": true
  },
  {
    "review_id": "162556848",
    "review": "Gran juego si te gusta el Señor de los Anillos. Recomendable, entretenido y divertido.",
    "voted_up": true
  },
  {
    "review_id": "107877111",
    "review": "UNA PIJA",
    "voted_up": false
  },
  {
    "review_id": "129136094",
    "review": "UNA PUTA MIERDA",
    "voted_up": false
  },
  {
    "review_id": "149782560",
    "review": "Muy buen producto de la franquicia lego",
    "voted_up": true
  },
  {
    "review_id": "200325878",
    "review": "Es un juegazo de lego, súper recomendado, tiene para viciarlo bastante",
    "voted_up": true
  },
  {
    "review_id": "115757059",
    "review": "es una garcha",
    "voted_up": false
  },
  {
    "review_id": "209008057",
    "review": "nostalgico y entretenido, mas si es en coperativo",
    "voted_up": true
  },
  {
    "review_id": "92758676",
    "review": "De los mejores de Lego que he jugado",
    "voted_up": true
  },
  {
    "review_id": "155509529",
    "review": "no va jolin",
    "voted_up": false
  },
  {
    "review_id": "114154449",
    "review": "Ni siquiera puedo jugarlo, la pantalla se minimiza a cada rato.\nPésimo.",
    "voted_up": false
  },
  {
    "review_id": "119912528",
    "review": "Muy entretenido y chido, lo había completado dos veces en otra plataformas, lo recomiendo, en lo personal prefiero el 1 a el 2",
    "voted_up": true
  },
  {
    "review_id": "115122334",
    "review": "una masa pa. no importa lo viejo que sea sigue estando god",
    "voted_up": true
  },
  {
    "review_id": "120780330",
    "review": "Increíble que un juego del 2012 siga teniendo tal cantidad de bugs.\n\nSi me dicen que lo ha hecho Bugisoft, me lo creo.",
    "voted_up": false
  },
  {
    "review_id": "133736300",
    "review": "podes usar a spiderman si es que no te anda el otro 11/10",
    "voted_up": true
  },
  {
    "review_id": "161280807",
    "review": "lo triste es cuando se acaba",
    "voted_up": true
  },
  {
    "review_id": "150198062",
    "review": "las misiones se repiten demasiado",
    "voted_up": false
  },
  {
    "review_id": "76775241",
    "review": "se cierra el juego despues de la persecucion...que puto desastre",
    "voted_up": false
  },
  {
    "review_id": "12515513",
    "review": "es un muy buen juego",
    "voted_up": false
  },
  {
    "review_id": "165745117",
    "review": "buen juego tío",
    "voted_up": true
  },
  {
    "review_id": "120243410",
    "review": "El mejor juego LEGO que existe.",
    "voted_up": true
  },
  {
    "review_id": "58023701",
    "review": "Es un juego super divertido, te encuentras dentro de las películas haciendo todo a tu gusto y tiempo.",
    "voted_up": true
  },
  {
    "review_id": "208138853",
    "review": "Tiene buenas partes pero también muchas repetitivas, lo bueno es que tienes 3 historias diferentes pero le falta explicar algo mas de la historia",
    "voted_up": false
  },
  {
    "review_id": "131482635",
    "review": "porque si te gusta el hobit",
    "voted_up": true
  },
  {
    "review_id": "104999882",
    "review": "definitavente no lo compren el juego inicia y al los 4 segundos te saca no recomendable",
    "voted_up": false
  },
  {
    "review_id": "31214466",
    "review": "Muy entretenido para pasar el rato :D!\nEspero sacaran mas secuelas de este.",
    "voted_up": true
  },
  {
    "review_id": "91488014",
    "review": "Buenardo, te la re vivís, más que el Battlefront 2",
    "voted_up": true
  },
  {
    "review_id": "88308058",
    "review": "esta feo el juego por que no tiene sonido la pregunta es por que",
    "voted_up": false
  },
  {
    "review_id": "191230759",
    "review": "Será buen juego, tal vez, pero si eres de pc y no tienes un mando a la mano, no lo compres, simple, saludos.",
    "voted_up": false
  },
  {
    "review_id": "36122763",
    "review": "Me encanta: lego sigue a si sorprediendo a lo usuarios 10/10",
    "voted_up": true
  },
  {
    "review_id": "48109507",
    "review": "Mal juego, muchos bugs.",
    "voted_up": false
  },
  {
    "review_id": "159936781",
    "review": "[i] TODO ES FABULOSOOOOOO [/i]",
    "voted_up": true
  },
  {
    "review_id": "115395872",
    "review": "es un buen juego, pero ya no es lo mismo que antes",
    "voted_up": false
  },
  {
    "review_id": "48152401",
    "review": "Es demasiado entretenido aunque es más divertido jugarlo entre 2 personas",
    "voted_up": true
  },
  {
    "review_id": "187920046",
    "review": "juegazo, esto es infancia bro",
    "voted_up": true
  },
  {
    "review_id": "172297525",
    "review": "ta weno",
    "voted_up": true
  },
  {
    "review_id": "10727272",
    "review": "no me funciona",
    "voted_up": false
  },
  {
    "review_id": "184816289",
    "review": "Excelente juego, controles extraños",
    "voted_up": true
  },
  {
    "review_id": "165022383",
    "review": "esta chido legod",
    "voted_up": true
  },
  {
    "review_id": "208648410",
    "review": "esta bueno",
    "voted_up": true
  },
  {
    "review_id": "21389315",
    "review": "Para niños de 3 años mecanicas repetitivas y facil.",
    "voted_up": false
  },
  {
    "review_id": "170267694",
    "review": "Hulk es demasiado fuerte y huele mal",
    "voted_up": false
  },
  {
    "review_id": "208288761",
    "review": "realmente pense q era mejor pero no es taan bueno como otros legos de la franquisia",
    "voted_up": false
  },
  {
    "review_id": "155668070",
    "review": "ta bueno",
    "voted_up": true
  },
  {
    "review_id": "115361741",
    "review": "ta weno  compralo",
    "voted_up": true
  },
  {
    "review_id": "145623692",
    "review": "manso juego",
    "voted_up": true
  },
  {
    "review_id": "187965774",
    "review": "Valla basura los controles.",
    "voted_up": false
  },
  {
    "review_id": "149621160",
    "review": "El juego se crashea de la nada mientras exploro el mundo abierto.Ya me pasó cómo 4 veces.",
    "voted_up": false
  },
  {
    "review_id": "160152672",
    "review": "Ta bueno",
    "voted_up": true
  },
  {
    "review_id": "28919582",
    "review": "Es un buen juego pero esta \nLleno de bugs que te impiden\nTerminar el juego",
    "voted_up": false
  },
  {
    "review_id": "203553074",
    "review": "no me gusto",
    "voted_up": false
  },
  {
    "review_id": "194227593",
    "review": "no me deja abrir el juego y es la verdad mi pc si lo corre",
    "voted_up": false
  },
  {
    "review_id": "28331777",
    "review": "muy bueno la verdad....toda las pelis bn\nrealizadas y muy comicas m rei mucho\nse los recomiendo al 100%",
    "voted_up": true
  },
  {
    "review_id": "184080888",
    "review": "Tiene un par de bugs que te fastidian la partida, una pena",
    "voted_up": false
  },
  {
    "review_id": "121298981",
    "review": "Simplemente un juegazo, 10/10. Nunca lo habia jugado, y sobrepasó mis expectativas MUCHISIMO.",
    "voted_up": true
  },
  {
    "review_id": "69682529",
    "review": "esta buenisimo recomendado",
    "voted_up": true
  },
  {
    "review_id": "170263877",
    "review": "No ta bien",
    "voted_up": false
  },
  {
    "review_id": "78596486",
    "review": "los controles son horribles",
    "voted_up": false
  },
  {
    "review_id": "130941072",
    "review": "Mira es bueno pero, ve por un marvel avengers o otro juego de lego este esta muerto aunque esta en nuestros corazones",
    "voted_up": false
  },
  {
    "review_id": "19717708",
    "review": "Excelente juego, muy divertido aunque en algunas partes se vuelve tedioso y repetitivo",
    "voted_up": true
  },
  {
    "review_id": "203243661",
    "review": "Eterno, desordenado, innecesario",
    "voted_up": false
  },
  {
    "review_id": "175689478",
    "review": "Juegazo, 10/10 tiene algunos bugs pero nada grave",
    "voted_up": true
  },
  {
    "review_id": "198302036",
    "review": "Buena juego, recomendado",
    "voted_up": true
  },
  {
    "review_id": "188139932",
    "review": "buen juego tiene varios personajes y buena historia",
    "voted_up": true
  },
  {
    "review_id": "20699172",
    "review": "se acaban haciendo repetitivos muchas de las mecanicas ingame",
    "voted_up": false
  },
  {
    "review_id": "142380864",
    "review": "Fulll ZZZZ el juego.",
    "voted_up": false
  },
  {
    "review_id": "78770616",
    "review": "El juego se crashea cuando encuentras a gandalf/saruman el blanco en el bosque",
    "voted_up": false
  },
  {
    "review_id": "117619198",
    "review": "10/10 muy buen juego",
    "voted_up": true
  },
  {
    "review_id": "114197081",
    "review": "esta bueno pero tenes que jugarlo mucho para pasartelo asi que no lo recomiendo",
    "voted_up": false
  },
  {
    "review_id": "140284277",
    "review": "Cada vez que abro el juego se cierra solo.",
    "voted_up": false
  },
  {
    "review_id": "74420782",
    "review": "medio raro el jueguito",
    "voted_up": false
  },
  {
    "review_id": "159170881",
    "review": "Es buen juego",
    "voted_up": true
  },
  {
    "review_id": "93388444",
    "review": "Besto juego si eres fan de esta saga, lo recomiendo full",
    "voted_up": true
  },
  {
    "review_id": "128588057",
    "review": "perfecto, hermoso",
    "voted_up": true
  },
  {
    "review_id": "132349431",
    "review": "una poronga",
    "voted_up": false
  },
  {
    "review_id": "202698046",
    "review": "muy genial",
    "voted_up": true
  },
  {
    "review_id": "83156482",
    "review": "¡Juegaso! Para todas las edades. Imprescindible si sos fan de Jurassic Park.",
    "voted_up": true
  },
  {
    "review_id": "162892236",
    "review": "juegazo de la play 3",
    "voted_up": true
  },
  {
    "review_id": "92636752",
    "review": "Me da miedo cuando Yoda se desarma",
    "voted_up": false
  },
  {
    "review_id": "115624346",
    "review": "EL JUEGO ES MUY BUENO, ES MAS ME PASE LA 24HS Y LO TERMINE RECIEN LO RECOMIENDO MUCHO",
    "voted_up": true
  },
  {
    "review_id": "147572525",
    "review": "en juego es FACHA",
    "voted_up": true
  },
  {
    "review_id": "155531726",
    "review": "ta bueno  :)",
    "voted_up": true
  },
  {
    "review_id": "134151296",
    "review": "es super incomodo de jugar y se ve super trucho",
    "voted_up": false
  },
  {
    "review_id": "73809006",
    "review": "Divertido, desafiante a ratos y con la magia propia de un juego de Lego con temática \"tolkeniana\".",
    "voted_up": true
  },
  {
    "review_id": "161091000",
    "review": "MUY BUENO",
    "voted_up": true
  },
  {
    "review_id": "206501271",
    "review": "Está bonito",
    "voted_up": true
  },
  {
    "review_id": "202719180",
    "review": "Es muy buen juego pero tiene muchos bugs y de la nada se crashea.",
    "voted_up": false
  },
  {
    "review_id": "148422501",
    "review": "masomenos, es estresante a cierto punto+",
    "voted_up": false
  },
  {
    "review_id": "172061181",
    "review": "fumate uno y quedate pancho jugando esto, no importa cuando leas esto",
    "voted_up": true
  },
  {
    "review_id": "151260530",
    "review": "Lo recordaba mas chido pero naah :)",
    "voted_up": true
  },
  {
    "review_id": "178310592",
    "review": "Todo es fabuloso",
    "voted_up": true
  },
  {
    "review_id": "130945332",
    "review": "Cuando lean esto, posiblemente ya tenga mas de 50 horas jugadas en este juego",
    "voted_up": true
  },
  {
    "review_id": "36773156",
    "review": "Juego muy bueno y entretenido. Me sorprendio.  10/10",
    "voted_up": true
  },
  {
    "review_id": "56051976",
    "review": "¡¡¡Entrega de LEGO imperdible!!!",
    "voted_up": true
  },
  {
    "review_id": "161899137",
    "review": "eta chuli \r\npd :no hay tetas",
    "voted_up": true
  },
  {
    "review_id": "130033078",
    "review": "nose porq lo compre pero ta bueno ññññññ",
    "voted_up": true
  },
  {
    "review_id": "16788264",
    "review": "SI ESTA BUENO PERO NO ME DEJA ABRIRLO SOLO JUGUE 3 NV",
    "voted_up": false
  },
  {
    "review_id": "203330805",
    "review": "Entretenido :)",
    "voted_up": true
  },
  {
    "review_id": "128446877",
    "review": "es un juego super bueno",
    "voted_up": true
  },
  {
    "review_id": "178348157",
    "review": "Un juego con bastantes bugs si no se juega limitado a 30fps. Por lo demás fino, juego nostálgico",
    "voted_up": true
  },
  {
    "review_id": "182901181",
    "review": "Si te gusta Lego y la trilogía de SDLA, no te lo pierdas. Es como verte las pelis pero con toques de humor. Lo recomiendo!",
    "voted_up": true
  },
  {
    "review_id": "117202044",
    "review": "muy buen juego",
    "voted_up": true
  },
  {
    "review_id": "157154795",
    "review": "Para estos tiempos, esta malisimo. aburrido. nada claro. totalmente arrepentido.",
    "voted_up": false
  },
  {
    "review_id": "34820501",
    "review": "Mira que amo lego con toda mi alma pero este es el peor lo siento",
    "voted_up": false
  },
  {
    "review_id": "190869698",
    "review": "es nostalgico",
    "voted_up": true
  },
  {
    "review_id": "44398552",
    "review": "Un juego bastante extenso pero entretenido e interesante.\nA esta fecha, esperamos Fallen Kigdom como DLC.",
    "voted_up": true
  },
  {
    "review_id": "105466112",
    "review": "Funciona perfectamente en este portatil que compré hace ya más de seis años.",
    "voted_up": true
  },
    {
    "review_id": "95682135",
    "review": "ta piola y relajante",
    "voted_up": true
  },
  {
    "review_id": "165343759",
    "review": "es una obra de arte es hermoso es lo mejor",
    "voted_up": true
  },
  {
    "review_id": "118073607",
    "review": "esta piola y mucha variedad de personajes",
    "voted_up": true
  },
  {
    "review_id": "88945932",
    "review": "Este juego comparado con la entrega anterior es una mierda. \nPorfa no te lo compres, no te lo recomiendo para nada.\n(1/10)",
    "voted_up": false
  },
  {
    "review_id": "205577422",
    "review": "ta weno",
    "voted_up": true
  },
  {
    "review_id": "97515541",
    "review": "ta god",
    "voted_up": true
  },
  {
    "review_id": "124887028",
    "review": "es mega divertida la trama :)",
    "voted_up": true
  },
  {
    "review_id": "36869800",
    "review": "Juego muy completo y adictivo",
    "voted_up": true
  },
  {
    "review_id": "114054201",
    "review": "Un gran juego, aunque a primera vista parezca un juego infantil te garantizo risas y diversion",
    "voted_up": true
  },
  {
    "review_id": "89783222",
    "review": "Me encanto",
    "voted_up": true
  },
  {
    "review_id": "212197789",
    "review": "Es un juego interesante, funciona si quieres relajarte aunque te relaja demasiado y te quedas dormido. :P",
    "voted_up": true
  },
  {
    "review_id": "80748447",
    "review": "el juego iba demasiado lagueado y no es por mi computadora ya que rebaso los requisitos recomendados",
    "voted_up": false
  },
  {
    "review_id": "207692657",
    "review": "Muy lindo me hizo llorar, la musica muy linda",
    "voted_up": true
  },
  {
    "review_id": "206353999",
    "review": "Mal. no he podido jugar todavía, compré la version completa y me dice que es friends pass",
    "voted_up": false
  },
  {
    "review_id": "178541173",
    "review": "lo mejor del mundo para amantes de los comics",
    "voted_up": true
  },
  {
    "review_id": "156003659",
    "review": "es mejor el 1 pero este igual esta bueno :)",
    "voted_up": true
  },
  {
    "review_id": "188446576",
    "review": "ta nice",
    "voted_up": true
  },
  {
    "review_id": "91660604",
    "review": "Tremenda mierda de juego se pueden ir a carajo no lo compren",
    "voted_up": false
  },
  {
    "review_id": "62991944",
    "review": "constantemente se pierde el progreso, dificil de volverlo a jugar donde lo deje",
    "voted_up": false
  },
  {
    "review_id": "66315597",
    "review": "El problema es w10, el juego falla continuamente para comenzar.",
    "voted_up": false
  },
  {
    "review_id": "77848315",
    "review": "que juego de mierda se me bugueo el juego mierda",
    "voted_up": false
  },
  {
    "review_id": "38557871",
    "review": "Me va muy Lag :c aunque tengo una PC muy buena pero el juego es muy bueno",
    "voted_up": true
  },
  {
    "review_id": "176193373",
    "review": "esta perro",
    "voted_up": true
  },
  {
    "review_id": "103512270",
    "review": "Muy lindo Juego... relajante.. .algo corto. Pero es genial! recomendado",
    "voted_up": true
  },
  {
    "review_id": "52424913",
    "review": "Increíble, una muy buena mejora respecto a los demás con pequeños detalles que se notan :) Lo dicen mis logros conseguidos en el juego ;P",
    "voted_up": true
  },
  {
    "review_id": "189549460",
    "review": "No me gusta y punto",
    "voted_up": false
  },
  {
    "review_id": "159620978",
    "review": "juego entretenido al cual le vas a dedicar muchas horas de juego, gran variedad de personajes",
    "voted_up": true
  },
  {
    "review_id": "94458049",
    "review": "esta bueno pero son un poco incomodos los controles con teclano es necesario un mando (esto afecta mucho la jugabilidad)",
    "voted_up": true
  },
  {
    "review_id": "109198659",
    "review": "este juego no se puede jugar online tiene muchos errores",
    "voted_up": false
  },
  {
    "review_id": "206443457",
    "review": "El jeugo es bastante mediocre, los zombis no dan miedo de noche. Prefiero el 1",
    "voted_up": false
  },
  {
    "review_id": "89604249",
    "review": "Es muy buen juego a mi me gusto porque demuestran muchas cosas que pasan en las peliculas y es genial para mi.",
    "voted_up": true
  },
  {
    "review_id": "175185864",
    "review": "juego aburrido, muy bonito pero no me ha gustado la jugabilidad",
    "voted_up": false
  },
  {
    "review_id": "117548315",
    "review": "mmm no me gusta el mapa abierto ni las historia y pues... esta mejor el primero.",
    "voted_up": false
  },
  {
    "review_id": "149196999",
    "review": "Se me cierra 4 veces por cada punto de control, lleno de bugs el juego, gasten en el de DC no en este",
    "voted_up": false
  },
  {
    "review_id": "175699306",
    "review": "Un juego de puzzles de lego con historia, visualmente un 10, te dará 2-3h de diversión, muy recomendable pero mejor comprarlo en oferta.",
    "voted_up": true
  },
  {
    "review_id": "129225082",
    "review": "Es muy entretenido, solo quise jugar 1 hora al día y siempre me paso a 4 horas al día, F :v",
    "voted_up": true
  },
  {
    "review_id": "198842826",
    "review": "Una película completa que no se puede skipear cada vez que terminás una misión.",
    "voted_up": false
  },
  {
    "review_id": "211450767",
    "review": "gran juego",
    "voted_up": true
  },
  {
    "review_id": "101066454",
    "review": "una cagada ABRO el juego entro pasa 3 segundo y se congela lpm",
    "voted_up": false
  },
  {
    "review_id": "82194196",
    "review": "es un juego muy divertido, recomendado",
    "voted_up": true
  },
  {
    "review_id": "99527944",
    "review": "Demasiado chill, muy recomendable para desconectar de todo",
    "voted_up": true
  },
  {
    "review_id": "90502123",
    "review": "no se compara con el 1",
    "voted_up": false
  },
  {
    "review_id": "94204027",
    "review": "Un juego sumamente bello, placentero de jugar y adecuado para todas las edades. Recomendado.",
    "voted_up": true
  },
  {
    "review_id": "104661015",
    "review": "Muy buen juego y los DLC lo hacen más divertido y entretenido",
    "voted_up": true
  },
  {
    "review_id": "78618614",
    "review": "es entretenido y respeta mucho el universo marel, se nota el cariño y casi no hay glitches",
    "voted_up": true
  },
  {
    "review_id": "118826757",
    "review": "ta piola",
    "voted_up": true
  },
  {
    "review_id": "206271510",
    "review": "Servidores lag.",
    "voted_up": false
  },
  {
    "review_id": "86161105",
    "review": "Bastante decepcionante teniendo en cuenta lo buena que fue la entrega anterior.",
    "voted_up": false
  },
  {
    "review_id": "103560550",
    "review": "Lo mejor de una infancia",
    "voted_up": true
  },
  {
    "review_id": "200881050",
    "review": "Buen juego",
    "voted_up": true
  },
  {
    "review_id": "104391668",
    "review": "visualmente genial aunque el juego es muy corto.",
    "voted_up": true
  },
  {
    "review_id": "65879077",
    "review": "Otro gran juego de LEGO. Muy amplio y con mucho que investigar y desbloquear.",
    "voted_up": true
  },
  {
    "review_id": "113900853",
    "review": "ta bien",
    "voted_up": true
  },
  {
    "review_id": "205194659",
    "review": "Hermosa obra maestra, muy entretenido y original",
    "voted_up": true
  },
  {
    "review_id": "61540001",
    "review": "Jugabilidad muy mala... haciendo que te canses del juego por detalles como saltar o activar dispositivos. mucho mejor Marvel 1.",
    "voted_up": false
  },
  {
    "review_id": "205035445",
    "review": "Es un juego sencillo que se ve y se escucha bien. Es amigable con personas que son jugadores muy muy casuales.",
    "voted_up": true
  },
  {
    "review_id": "101343098",
    "review": "totalmente god",
    "voted_up": true
  },
  {
    "review_id": "199061189",
    "review": "Juego corto, y absolutamente precioso. Para una tarde tranquila y sencilla.",
    "voted_up": true
  },
  {
    "review_id": "85347561",
    "review": "muy aburrido, para lo grande que han sido los juegos de lego, este deja bastante que desear",
    "voted_up": false
  },
  {
    "review_id": "36633082",
    "review": "Va muy lag...",
    "voted_up": false
  },
  {
    "review_id": "51259581",
    "review": "El peor juego de LEGO lleno de bugs y sin personalidad",
    "voted_up": false
  },
  {
    "review_id": "117607050",
    "review": "solo si sos fan pero es muy bueno",
    "voted_up": true
  },
  {
    "review_id": "106330246",
    "review": "ta bueno",
    "voted_up": true
  },
  {
    "review_id": "189478922",
    "review": "tiene muchos problemas el juego, se me bugueo uno de los trofeos y me es imposible sacarlo \r\nestaria bueno una actualizacion para eliminar eso",
    "voted_up": false
  },
  {
    "review_id": "141557652",
    "review": "pero que le pasa a los controles",
    "voted_up": false
  },
  {
    "review_id": "206600854",
    "review": "Juegazoooooooooooooooo, recomendado para jugar con amigos o familia vroh :3",
    "voted_up": true
  },
  {
    "review_id": "62819345",
    "review": "Tematica excelente",
    "voted_up": true
  },
  {
    "review_id": "93333156",
    "review": "siempre me divierte el lego marvel",
    "voted_up": true
  },
  {
    "review_id": "204824547",
    "review": "Si tienes mas de 2 años mentales, no lo juegues.",
    "voted_up": false
  },
  {
    "review_id": "94836227",
    "review": "crasheos el juego",
    "voted_up": false
  },
  {
    "review_id": "59752464",
    "review": "es malo",
    "voted_up": false
  },
  {
    "review_id": "74667964",
    "review": "esta chulo",
    "voted_up": true
  },
  {
    "review_id": "198584295",
    "review": "ta bueno",
    "voted_up": true
  },
  {
    "review_id": "78205308",
    "review": "algunas carreras y puzzles son TAN difíciles que son prácticamente imposibles y pretenden que este juego sea apto para todos, debería darles vergüenza.",
    "voted_up": false
  },
  {
    "review_id": "186775480",
    "review": "Las construcciones son más tediosas que desafiantes. Los mapas son lentos y la dificultad es muy fácil. Deberían clasificarlo como juego infantil.",
    "voted_up": false
  },
  {
    "review_id": "169778509",
    "review": "Buena Variedad de Personajes, Misiones y Niveles. Pero lleno de bugs que crashean el juego",
    "voted_up": false
  },
  {
    "review_id": "205907251",
    "review": "Los servidores no funcionan, va todo lagueado",
    "voted_up": false
  },
  {
    "review_id": "205947691",
    "review": "Caro para su duración pero es completo peak, se siente literalmente como jugar con unos legos con tu amigo",
    "voted_up": true
  },
  {
    "review_id": "46789424",
    "review": "Muy divertido.",
    "voted_up": true
  },
  {
    "review_id": "139764195",
    "review": "Buen juego",
    "voted_up": true
  },
  {
    "review_id": "195932789",
    "review": "Muy lento en comparacion al otro lego marvel, el nivel de agua es aburridisimo",
    "voted_up": false
  },
  {
    "review_id": "53107902",
    "review": "Personalmente creo que el peor de todos los que he jugado, historia aburrida, situaciones poco intuitivas.",
    "voted_up": false
  },
  {
    "review_id": "106370385",
    "review": "buen juego de lego",
    "voted_up": true
  },
  {
    "review_id": "58869873",
    "review": "esta genial",
    "voted_up": true
  },
  {
    "review_id": "194653473",
    "review": "personalmente, me parece mejor que el 1",
    "voted_up": true
  },
  {
    "review_id": "137061427",
    "review": "He completado CADA UNO DE LOS OBJETIVOS DEL JUEGO, y mi propósito era tener la medalla de todos los logros completados pero... se ha bugeado.",
    "voted_up": false
  },
    {
    "review_id": "47663533",
    "review": "No se guardan las partidas",
    "voted_up": false
  },
  {
    "review_id": "93333968",
    "review": "ta weno compralo",
    "voted_up": true
  },
  {
    "review_id": "61541739",
    "review": "ta chido",
    "voted_up": true
  },
  {
    "review_id": "40431064",
    "review": "¿Alguien sabe si está la última parte? Porfavor",
    "voted_up": false
  },
  {
    "review_id": "50887299",
    "review": "Es bastante mediocre, a mi personalmente me ha aburrido, y eso que las sagas de tolkien me gustan",
    "voted_up": false
  },
  {
    "review_id": "179767277",
    "review": "sencillo pero me encanta",
    "voted_up": true
  },
  {
    "review_id": "112650223",
    "review": "Esta buenardisimo",
    "voted_up": true
  },
  {
    "review_id": "77261991",
    "review": "la historia esta incompleta",
    "voted_up": false
  },
  {
    "review_id": "67785877",
    "review": "Muy buena experiencia, de mis favoritos de Lego Star wars por ahora.",
    "voted_up": true
  },
  {
    "review_id": "159936860",
    "review": "TODO ES FABULOSOOOOOO",
    "voted_up": true
  },
  {
    "review_id": "48044830",
    "review": "una caca no lo recomiendo",
    "voted_up": false
  },
  {
    "review_id": "84169726",
    "review": "Podrían haber esperado un poco y no dejar el juego a medias. Chusta.",
    "voted_up": false
  },
  {
    "review_id": "199825016",
    "review": "las peores 3 horas de mi vida",
    "voted_up": false
  },
  {
    "review_id": "57598199",
    "review": "Me agrada jugar lo que en una película",
    "voted_up": true
  },
  {
    "review_id": "52285060",
    "review": "Bueeeenardo, me encanto",
    "voted_up": true
  },
  {
    "review_id": "60940444",
    "review": "un juego totalmente renovado excelente elección con mecanicas completamente distintas",
    "voted_up": true
  },
  {
    "review_id": "48050518",
    "review": "Una adaptación genial",
    "voted_up": true
  },
  {
    "review_id": "47526611",
    "review": "Bueno para tirarse una risa o dejar a los hijos jugandolo pero nada nuevo",
    "voted_up": true
  },
  {
    "review_id": "134533553",
    "review": "Una mierda",
    "voted_up": false
  },
  {
    "review_id": "133778003",
    "review": "esto es igual que game of trones, nunca llegaron los dragones",
    "voted_up": false
  },
  {
    "review_id": "152971276",
    "review": "El rendimiento del juego es directamente proporcional a la reputación de J.K. Rowling",
    "voted_up": false
  },
  {
    "review_id": "148052255",
    "review": "No esta completo el juego, le falta la tercera película",
    "voted_up": false
  },
  {
    "review_id": "83845435",
    "review": "es altamente recomendable, es muy buen juego, me gusta la cinemática que tiene y los efectos es muy entretenido el juego",
    "voted_up": true
  },
  {
    "review_id": "158743617",
    "review": "Los diálogos son MUY malos, no le pusieron ganas a las voces (Por lo menos en español)",
    "voted_up": false
  },
  {
    "review_id": "47214938",
    "review": "BUEN JUEGO",
    "voted_up": true
  },
  {
    "review_id": "207588345",
    "review": "Es divertido",
    "voted_up": true
  },
  {
    "review_id": "93194415",
    "review": "ME CAGO EN LA LECHE FRITA QUE SOLO SON LAS 2 PRIMERAS PELICULAS Y LA TERCERA NO ESTA CAGUEN LOS DEMONIOS DE TOLKIEN",
    "voted_up": false
  },
  {
    "review_id": "52081678",
    "review": "A precio de oferta vale mucho la pena, y más si eres fan de star wars.",
    "voted_up": true
  },
  {
    "review_id": "58675831",
    "review": "grande los legos",
    "voted_up": true
  },
  {
    "review_id": "51956801",
    "review": "gran historia",
    "voted_up": true
  },
  {
    "review_id": "117048919",
    "review": "excelente, el mejor juego de la saga Harry Potter, con tonos de humor al mejor estilo lego",
    "voted_up": true
  },
  {
    "review_id": "150234457",
    "review": "No esta a la altura de Lego el señor de los anillos ni de lejos, por lo demás bien. Solo quiero que salga el juego terminado",
    "voted_up": false
  },
  {
    "review_id": "154425341",
    "review": "A comparación de la primer entrega (Años 1-4) ha mejorado increíblemente y es mil veces mejor. Recomendado!",
    "voted_up": true
  },
  {
    "review_id": "65705811",
    "review": "si te gusta la saga del hobbit y el señor de los anillos te gustará el juego.",
    "voted_up": true
  },
  {
    "review_id": "91717485",
    "review": "Muy bueno !",
    "voted_up": true
  },
  {
    "review_id": "145022246",
    "review": "JUEGON 11/10 EL MEJOR DE TODOS",
    "voted_up": true
  },
  {
    "review_id": "116445821",
    "review": "no se puede jugar con teclado",
    "voted_up": false
  },
  {
    "review_id": "174226045",
    "review": "cualquier LEGO es un buen juego",
    "voted_up": true
  },
  {
    "review_id": "88959580",
    "review": "el juego esta bueno pero se bugea cuando jugas con joystick",
    "voted_up": false
  },
  {
    "review_id": "58507922",
    "review": "Amo este juego",
    "voted_up": true
  },
  {
    "review_id": "165772162",
    "review": "hay un bug en una misión en la que bb8 se queda en el techo de la pantalla y no podes hacer nada",
    "voted_up": false
  },
  {
    "review_id": "115827767",
    "review": "Está bueno es divertido compralo",
    "voted_up": true
  },
  {
    "review_id": "209563796",
    "review": "No les perdono que tuviesen los huevos de sacarlo sin haber terminado las películas y ni si quiera sacar la expansión que estaba planeada",
    "voted_up": false
  },
  {
    "review_id": "122881661",
    "review": "muy chulo",
    "voted_up": true
  },
  {
    "review_id": "61660433",
    "review": "te pasaras mas tiempo recolectando las *piezas* que jugando al propio juego",
    "voted_up": false
  },
  {
    "review_id": "24664373",
    "review": "Muy buen juego entretenido nunca hago reseñas pero la verdad este juego merece una",
    "voted_up": true
  },
  {
    "review_id": "73341640",
    "review": "buen juego",
    "voted_up": true
  },
  {
    "review_id": "108055688",
    "review": "Mecánicas poco divertidas y no incluye la historia completa.",
    "voted_up": false
  },
  {
    "review_id": "71505122",
    "review": "es muy bueno y entretenido",
    "voted_up": true
  },
  {
    "review_id": "155091148",
    "review": "Gracias abuelito por regalarme el juego!",
    "voted_up": true
  },
  {
    "review_id": "73158294",
    "review": "Un juego divertido y con el que pasaras un buen rato si te gusta la Tierra Media. Ademas pueden jugar dos personas",
    "voted_up": true
  },
  {
    "review_id": "111716505",
    "review": "esta chevere recomendados para personas con paciencia o masoquistas",
    "voted_up": true
  },
  {
    "review_id": "116758479",
    "review": "Falta la tercera y ultima parte de la saga del Hobbit, lo que hace que le juego quede incompleto.",
    "voted_up": false
  },
  {
    "review_id": "189424413",
    "review": "mierdon el juego",
    "voted_up": false
  },
  {
    "review_id": "57954864",
    "review": "muy simple, nada de complejidad, muy infantil",
    "voted_up": false
  },
  {
    "review_id": "95337930",
    "review": "Muy bueno",
    "voted_up": true
  },
  {
    "review_id": "78492506",
    "review": "Bastante entretenido en coop local, para pasar el rato esta bien.",
    "voted_up": true
  },
  {
    "review_id": "61434632",
    "review": "LEGO siempre se luce con Star Wars",
    "voted_up": true
  },
  {
    "review_id": "70081777",
    "review": "La mejor saga de todos los tiempos",
    "voted_up": true
  },
  {
    "review_id": "60703730",
    "review": "Esta increible, y aun mas si eres un fan de lego y star wars",
    "voted_up": true
  },
  {
    "review_id": "141967954",
    "review": "buen juego lo unico malo que la tercera pelicula no esta",
    "voted_up": true
  },
  {
    "review_id": "59238591",
    "review": "Me gusto, es entretenido, hay algunos bugs pero los pude solucionar.",
    "voted_up": true
  },
  {
    "review_id": "20998035",
    "review": "Me dejo sin palabras",
    "voted_up": true
  },
  {
    "review_id": "16342654",
    "review": "lo recomiendo buen juego",
    "voted_up": true
  },
  {
    "review_id": "102459303",
    "review": "La jugabilidad es malisima",
    "voted_up": false
  },
  {
    "review_id": "116060684",
    "review": "Me encanta",
    "voted_up": true
  },
  {
    "review_id": "92056121",
    "review": "muy divertido pero igualmente es muy corto para un juego de lego",
    "voted_up": true
  },
  {
    "review_id": "61359410",
    "review": "Muy buen lego",
    "voted_up": true
  },
  {
    "review_id": "115549061",
    "review": "El peor juego de Lego. Aburrido, bugeado por todos lados y le falta la última película.",
    "voted_up": false
  },
  {
    "review_id": "137203810",
    "review": "El juego está incompleto. ¡¿Cómo se te ocurre?!",
    "voted_up": false
  },
  {
    "review_id": "72314454",
    "review": "muy bueno",
    "voted_up": true
  },
  {
    "review_id": "179755227",
    "review": "No compres esta maldita mierda, no puedes jugarla, después de 3 segundos estarás jodido, saludos",
    "voted_up": false
  },
  {
    "review_id": "88963675",
    "review": "increible juego hermano",
    "voted_up": true
  },
  {
    "review_id": "76164954",
    "review": "Es un juego genial en cuanto a jugabilidad, pero la falta de una adaptación de batalla de cinco ejércitos lo hace sentir realmente incompleto.",
    "voted_up": false
  },
  {
    "review_id": "130953009",
    "review": "es nostalgico",
    "voted_up": true
  },
  {
    "review_id": "157088442",
    "review": "Me gusta mucho la saga de LEGO. Me siento satisfecho y halagado al recibir esta exquisita obra videojueguística.",
    "voted_up": true
  },
  {
    "review_id": "183599204",
    "review": "JUEGO DE MIERDA NO SIRVE NI PARA DORMIR",
    "voted_up": false
  },
  {
    "review_id": "184553817",
    "review": "MUY bueno",
    "voted_up": true
  },
  {
    "review_id": "182269664",
    "review": "Vaya mierda de juego, esta tan bugueado que ni de el segundo mundo puedes pasar",
    "voted_up": false
  },
  {
    "review_id": "17755275",
    "review": "A mi me encanta mucho el juego y la verdad lo recomiendo. Lo único de malo que tiene es que tarda mucho en cargar",
    "voted_up": true
  },
  {
    "review_id": "184658248",
    "review": "Un juego de LEGO bastante subestimado. Me lo pasé genial jugándolo.",
    "voted_up": true
  },
  {
    "review_id": "175084410",
    "review": "El juego me trae recuerdos de cuando lo jugaba en una psvita, es muy buen juego y recomendado",
    "voted_up": true
  },
  {
    "review_id": "172754414",
    "review": "Me gusto e juego, muy entretenido",
    "voted_up": true
  },
  {
    "review_id": "191115273",
    "review": "apenas vi el nuevo sistema de construccion, lo odie, porque no hablan bien los personajes?",
    "voted_up": false
  },
  {
    "review_id": "87436959",
    "review": "Buen juego",
    "voted_up": true
  },
  {
    "review_id": "67338180",
    "review": "La mejor experiencia de mi vida, me recuerda a los primeros juegos. Es increible",
    "voted_up": true
  },
  {
    "review_id": "52323684",
    "review": "Entretenido, aunque los controles son un poco más complejos que los de otros juegos Lego",
    "voted_up": true
  },
  {
    "review_id": "152081947",
    "review": "es muy recomendable, variado, divertido y si eres fan de star wars lo difrutaras.",
    "voted_up": true
  },
  {
    "review_id": "112717851",
    "review": "muy buen juego y buenos graficos",
    "voted_up": true
  },
  {
    "review_id": "74482806",
    "review": "no pude jugarlo debido a los problemas de rendimiento que presenta, mucho tirones y bajones de fps sin solucion. malgaste mi dinero",
    "voted_up": false
  },
  {
    "review_id": "117815993",
    "review": "este juego esta muy bueno",
    "voted_up": true
  },
  {
    "review_id": "54969016",
    "review": "puta mierda de juego ni sirve los controles no puedes hacer nada",
    "voted_up": false
  },
  {
    "review_id": "124625720",
    "review": "Para fans de la Tierra Media",
    "voted_up": true
  },
  {
    "review_id": "42215888",
    "review": "Super juego, prueba jugarlo con un mando, por que solo con el teclado cansa mucho",
    "voted_up": true
  },
  {
    "review_id": "137856530",
    "review": "Historia 9.5/10, personajes 10/10, juego 9.5/10",
    "voted_up": true
  },
  {
    "review_id": "66999975",
    "review": "Nunca había jugado a juegos de LEGO y me sorprendió muchísimo. Me entretuvo muchísimo y además es muy fiel a la historia. Recomendado.",
    "voted_up": true
  },
  {
    "review_id": "127601123",
    "review": "esta buenaaarrdoo para jugar de a 2",
    "voted_up": true
  },
  {
    "review_id": "115815959",
    "review": "Uno de los mejores LEGO que probé en mí vida. Esto es emocionante. 8/10",
    "voted_up": true
  },
  {
    "review_id": "39124750",
    "review": "Esta guapo para jugar con amigos",
    "voted_up": true
  },
  {
    "review_id": "99995393",
    "review": "Incompleto. Ya les vale a los de lego.",
    "voted_up": false
  },
  {
    "review_id": "200157925",
    "review": "Como todos los juegos de LEGO, siempre hay algún bug. Fuera de eso lo recomiendo",
    "voted_up": true
  },
  {
    "review_id": "142534174",
    "review": "me quede bugueado y es re aburrido",
    "voted_up": false
  },
  {
    "review_id": "50136245",
    "review": "Muy divertido y muchísimo contenido! Los diálogos muy, muy bien integrados en el juego y una gran dosis de humor! Altamente recomendado",
    "voted_up": true
  },
  {
    "review_id": "37143156",
    "review": "Un juego magnifico para jugar con amigos",
    "voted_up": true
  },
  {
    "review_id": "44570915",
    "review": "esta bien. pero muy mal optimizado con varios crasheos",
    "voted_up": true
  },
  {
    "review_id": "180748969",
    "review": "Muy entretenido y perfecto para pasar el rato. Funciona perfecto en la Steam Deck.",
    "voted_up": true
  },
  {
    "review_id": "130452408",
    "review": "Lo jugamos juntos Lucas (5 años) y yo (38 años), nos hemos divertido mucho",
    "voted_up": true
  },
  {
    "review_id": "79021748",
    "review": "Es un juego muy corto pero a la vez logra que me harte de él, el primer juego personalmente lo disfrute pero este no.",
    "voted_up": false
  },
  {
    "review_id": "99080807",
    "review": "Intenté que me guste pero no cambie de opinion. Es mucho mejor el The Clone Wars y ni hablar de The Complete Saga",
    "voted_up": false
  },
  {
    "review_id": "81616183",
    "review": "Me gusta, de los legos mas complicados que jugue. Luego de hecho el 100% con todos los logros. El juego vale la pena completamente.",
    "voted_up": true
  },
  {
    "review_id": "178462875",
    "review": "JODER COMO AMO LEGO STAR WARS",
    "voted_up": true
  },
  {
    "review_id": "13600024",
    "review": "No puedo jugar, el juego se queda en una pantalla negra y se congela, lo que me hace reiniciar la PC y odio cuando eso sucede.",
    "voted_up": false
  },
  {
    "review_id": "47962336",
    "review": "Menos mal que salio gratis, por que menuda mierda.",
    "voted_up": false
  },
  {
    "review_id": "94632275",
    "review": "lo tuve que desinstalar porque esta mal optimizado, ando por 200 fps y de la nada baja a 20-30 fps",
    "voted_up": false
  },
  {
    "review_id": "162451760",
    "review": "Divertido, facil de entender y mucho mejor jugando con amigos, las posibilidades son muchas en el mundo de LEGO",
    "voted_up": true
  },
  {
    "review_id": "109252512",
    "review": "Se bugea en la primer mision",
    "voted_up": false
  },
  {
    "review_id": "129444791",
    "review": "Es divertido. Cualquier LEGO merece la pena.",
    "voted_up": true
  },
  {
    "review_id": "89332946",
    "review": "Segunda parte de la saga Harry Potter en version Lego, entretenido y divertido juego.",
    "voted_up": true
  },
  {
    "review_id": "36823292",
    "review": "voy a probarlo y luego daré un analisis :D",
    "voted_up": true
  },
  {
    "review_id": "170067308",
    "review": "No me gustó, pero vos jugalo igual.",
    "voted_up": true
  },
  {
    "review_id": "86216745",
    "review": "muy buen juego merece la pena",
    "voted_up": true
  },
  {
    "review_id": "78405937",
    "review": "te quiero LEGO nunca me faltes",
    "voted_up": true
  },
  {
    "review_id": "90583078",
    "review": "juego incompleto ¿donde esta la tercer parte de la SAGA? ME SIENTO ESTAFADO",
    "voted_up": false
  },
  {
    "review_id": "47782185",
    "review": "Los controles son una realmente mierda",
    "voted_up": false
  },
  {
    "review_id": "110597408",
    "review": "el de la play 2 era mejor",
    "voted_up": false
  },
  {
    "review_id": "108626832",
    "review": "Por mucho que lo intento no encuentro nada bueno en este juego",
    "voted_up": false
  },
  {
    "review_id": "166220734",
    "review": "Muy entretenido",
    "voted_up": true
  },
  {
    "review_id": "14838465",
    "review": "Tiene bugs y se cierra el juego solo",
    "voted_up": false
  },
  {
    "review_id": "166805469",
    "review": "Como el del Señor de los Anillos, pero peor.",
    "voted_up": true
  },
  {
    "review_id": "88156254",
    "review": "aaa no pero muy buenooooooooooo. 10/10",
    "voted_up": true
  },
  {
    "review_id": "24054578",
    "review": "En mitad de las misiones el juego se detiene y sale una ventana de windows que dice que dejo de funcionar.",
    "voted_up": false
  },
  {
    "review_id": "203460809",
    "review": "El peor juego de LEGO que he jugado",
    "voted_up": false
  },
  {
    "review_id": "192172935",
    "review": "Juego muy malo la verdad",
    "voted_up": false
  },
  {
    "review_id": "158105222",
    "review": "Es Lego bro, juegalo",
    "voted_up": true
  },
  {
    "review_id": "74383776",
    "review": "juego entretenido pero sin embargo esta incompleto ya que falta la batalla de los 5 reinos",
    "voted_up": true
  },
  {
    "review_id": "42021918",
    "review": "es una más que decente adaptacion de las pelis. Aún así tiene muchos bugs",
    "voted_up": true
  },
  {
    "review_id": "209380486",
    "review": "ES UNA POYINADA",
    "voted_up": true
  },
  {
    "review_id": "90254913",
    "review": "No está ni probado. Falla mucho.",
    "voted_up": false
  },
  {
    "review_id": "72710657",
    "review": "Es viejo pero es jugable (100%)",
    "voted_up": true
  },
  {
    "review_id": "60078813",
    "review": "es muy entretenido",
    "voted_up": true
  },
  {
    "review_id": "43065691",
    "review": "No se puede jugar con ratón, te obliga a jugar con las dos manos en el teclado o con mando.",
    "voted_up": false
  },
  {
    "review_id": "17164511",
    "review": "EL MEJOR JUEGO DEL MUNDO",
    "voted_up": true
  },
  {
    "review_id": "30624215",
    "review": "Buenos graficos, pero corto y con algunos fallos que bloquean el juego",
    "voted_up": false
  },
  {
    "review_id": "131294022",
    "review": "Finalmente conseguí el 100%, lo recomiendo seguro.",
    "voted_up": true
  },
  {
    "review_id": "107228526",
    "review": "En mi opinion muy superior a los 3 Lego Star Wars anteriores",
    "voted_up": true
  },
  {
    "review_id": "116081997",
    "review": "Es un clásico. Cumple con todos los estándares de los juegos de Lego.",
    "voted_up": true
  }
]
